{"DataSet": "MODIS", "coordinates": [{"lat": 22.184, "lon": -81}, {"lat": 22.744, "lon": -80}, {"lat": 22.743, "lon": -80}, {"lat": 22.749, "lon": -80}, {"lat": 28.524, "lon": -88}, {"lat": 22.19, "lon": -99}, {"lat": 25.069, "lon": -100}, {"lat": 25.071, "lon": -100}, {"lat": 33.411, "lon": -111}, {"lat": 33.422, "lon": -111}, {"lat": 33.414, "lon": -111}, {"lat": 33.411, "lon": -111}, {"lat": 33.425, "lon": -111}, {"lat": 33.422, "lon": -111}, {"lat": 27.612, "lon": -82}, {"lat": 26.952, "lon": -80}, {"lat": 26.799, "lon": -81}, {"lat": 26.727, "lon": -81}, {"lat": 23.041, "lon": -99}, {"lat": 23.04, "lon": -99}, {"lat": 22.057, "lon": -98}, {"lat": 40.622, "lon": -95}, {"lat": 40.359, "lon": -102}, {"lat": 40.357, "lon": -102}, {"lat": 38.697, "lon": -90}, {"lat": 38.694, "lon": -90}, {"lat": 39.005, "lon": -95}, {"lat": 38.995, "lon": -95}, {"lat": 38.357, "lon": -92}, {"lat": 38.215, "lon": -92}, {"lat": 37.888, "lon": -95}, {"lat": 37.886, "lon": -95}, {"lat": 37.561, "lon": -94}, {"lat": 37.281, "lon": -95}, {"lat": 37.28, "lon": -95}, {"lat": 36.882, "lon": -95}, {"lat": 30.796, "lon": -89}, {"lat": 30.797, "lon": -89}, {"lat": 48.792, "lon": -119}, {"lat": 48.792, "lon": -119}, {"lat": 46.726, "lon": -119}, {"lat": 46.327, "lon": -121}, {"lat": 46.325, "lon": -121}, {"lat": 40.543, "lon": -122}, {"lat": 40.29, "lon": -122}, {"lat": 40.288, "lon": -122}, {"lat": 38.919, "lon": -123}, {"lat": 38.093, "lon": -121}, {"lat": 37.605, "lon": -121}, {"lat": 37.384, "lon": -119}, {"lat": 37.241, "lon": -120}, {"lat": 36.57, "lon": -120}, {"lat": 36.568, "lon": -120}, {"lat": 36.441, "lon": -121}, {"lat": 34.095, "lon": -117}, {"lat": 34.119, "lon": -118}, {"lat": 22.017, "lon": -78}, {"lat": 22.03, "lon": -79}, {"lat": 22.033, "lon": -79}, {"lat": 22.032, "lon": -79}, {"lat": 22.03, "lon": -79}, {"lat": 22.043, "lon": -79}, {"lat": 22.041, "lon": -79}, {"lat": 22.04, "lon": -79}, {"lat": 22.051, "lon": -79}, {"lat": 22.071, "lon": -81}, {"lat": 22.179, "lon": -80}, {"lat": 22.242, "lon": -81}, {"lat": 22.479, "lon": -80}, {"lat": 22.478, "lon": -81}, {"lat": 22.406, "lon": -82}, {"lat": 22.404, "lon": -82}, {"lat": 22.591, "lon": -81}, {"lat": 22.589, "lon": -81}, {"lat": 22.801, "lon": -82}, {"lat": 22.855, "lon": -82}, {"lat": 22.854, "lon": -82}, {"lat": 22.828, "lon": -82}, {"lat": 22.653, "lon": -83}, {"lat": 22.659, "lon": -83}, {"lat": 22.798, "lon": -83}, {"lat": 22.807, "lon": -83}, {"lat": 22.93, "lon": -83}, {"lat": 22.929, "lon": -83}, {"lat": 22.997, "lon": -83}, {"lat": 26.005, "lon": -81}, {"lat": 26.004, "lon": -81}, {"lat": 26.535, "lon": -81}, {"lat": 26.534, "lon": -81}, {"lat": 26.969, "lon": -80}, {"lat": 26.968, "lon": -80}, {"lat": 27.167, "lon": -80}, {"lat": 27.166, "lon": -80}, {"lat": 27.229, "lon": -81}, {"lat": 27.227, "lon": -81}, {"lat": 27.223, "lon": -82}, {"lat": 27.235, "lon": -82}, {"lat": 27.234, "lon": -82}, {"lat": 27.232, "lon": -82}, {"lat": 27.244, "lon": -82}, {"lat": 27.442, "lon": -81}, {"lat": 27.441, "lon": -81}, {"lat": 27.429, "lon": -82}, {"lat": 28.489, "lon": -81}, {"lat": 28.488, "lon": -81}, {"lat": 28.486, "lon": -81}, {"lat": 28.497, "lon": -81}, {"lat": 29.278, "lon": -81}, {"lat": 29.619, "lon": -83}, {"lat": 29.883, "lon": -82}, {"lat": 29.882, "lon": -82}, {"lat": 29.951, "lon": -83}, {"lat": 30.037, "lon": -83}, {"lat": 30.046, "lon": -85}, {"lat": 30.044, "lon": -85}, {"lat": 30.058, "lon": -85}, {"lat": 30.076, "lon": -85}, {"lat": 30.074, "lon": -85}, {"lat": 30.478, "lon": -82}, {"lat": 30.484, "lon": -82}, {"lat": 30.482, "lon": -82}, {"lat": 30.478, "lon": -82}, {"lat": 30.487, "lon": -82}, {"lat": 30.499, "lon": -82}, {"lat": 30.497, "lon": -82}, {"lat": 30.496, "lon": -82}, {"lat": 30.494, "lon": -82}, {"lat": 30.323, "lon": -84}, {"lat": 30.506, "lon": -82}, {"lat": 30.505, "lon": -82}, {"lat": 30.332, "lon": -84}, {"lat": 30.189, "lon": -85}, {"lat": 30.187, "lon": -85}, {"lat": 30.198, "lon": -85}, {"lat": 30.248, "lon": -85}, {"lat": 30.526, "lon": -84}, {"lat": 30.652, "lon": -83}, {"lat": 30.557, "lon": -85}, {"lat": 30.939, "lon": -82}, {"lat": 30.938, "lon": -82}, {"lat": 30.948, "lon": -82}, {"lat": 30.947, "lon": -82}, {"lat": 30.77, "lon": -84}, {"lat": 30.927, "lon": -83}, {"lat": 30.906, "lon": -85}, {"lat": 31.304, "lon": -84}, {"lat": 31.557, "lon": -82}, {"lat": 31.459, "lon": -84}, {"lat": 31.659, "lon": -83}, {"lat": 31.659, "lon": -84}, {"lat": 31.668, "lon": -84}, {"lat": 31.63, "lon": -84}, {"lat": 31.673, "lon": -84}, {"lat": 31.831, "lon": -83}, {"lat": 32.171, "lon": -81}, {"lat": 32.175, "lon": -81}, {"lat": 31.94, "lon": -83}, {"lat": 31.939, "lon": -83}, {"lat": 32.185, "lon": -82}, {"lat": 31.929, "lon": -84}, {"lat": 32.052, "lon": -84}, {"lat": 32.64, "lon": -81}, {"lat": 32.475, "lon": -82}, {"lat": 32.496, "lon": -82}, {"lat": 32.628, "lon": -81}, {"lat": 32.626, "lon": -81}, {"lat": 32.354, "lon": -84}, {"lat": 32.363, "lon": -84}, {"lat": 32.333, "lon": -84}, {"lat": 32.331, "lon": -84}, {"lat": 32.448, "lon": -83}, {"lat": 32.374, "lon": -84}, {"lat": 32.373, "lon": -84}, {"lat": 32.724, "lon": -81}, {"lat": 32.549, "lon": -82}, {"lat": 32.547, "lon": -82}, {"lat": 31.854, "lon": -87}, {"lat": 32.315, "lon": -84}, {"lat": 32.814, "lon": -81}, {"lat": 32.812, "lon": -81}, {"lat": 32.664, "lon": -83}, {"lat": 32.663, "lon": -83}, {"lat": 33.002, "lon": -80}, {"lat": 32.752, "lon": -83}, {"lat": 32.746, "lon": -83}, {"lat": 32.913, "lon": -82}, {"lat": 33.18, "lon": -80}, {"lat": 32.633, "lon": -84}, {"lat": 33.026, "lon": -81}, {"lat": 33.055, "lon": -81}, {"lat": 32.651, "lon": -84}, {"lat": 32.967, "lon": -82}, {"lat": 32.082, "lon": -88}, {"lat": 33.174, "lon": -82}, {"lat": 33.173, "lon": -82}, {"lat": 33.119, "lon": -82}, {"lat": 33.184, "lon": -82}, {"lat": 33.182, "lon": -82}, {"lat": 33.02, "lon": -83}, {"lat": 33.156, "lon": -82}, {"lat": 33.013, "lon": -83}, {"lat": 32.974, "lon": -84}, {"lat": 32.973, "lon": -84}, {"lat": 33.541, "lon": -80}, {"lat": 33.552, "lon": -80}, {"lat": 33.095, "lon": -84}, {"lat": 33.104, "lon": -84}, {"lat": 33.232, "lon": -83}, {"lat": 33.231, "lon": -83}, {"lat": 33.161, "lon": -84}, {"lat": 33.358, "lon": -82}, {"lat": 33.367, "lon": -82}, {"lat": 33.752, "lon": -79}, {"lat": 33.717, "lon": -81}, {"lat": 33.434, "lon": -83}, {"lat": 33.682, "lon": -82}, {"lat": 33.858, "lon": -82}, {"lat": 39.48, "lon": -84}, {"lat": 39.286, "lon": -87}, {"lat": 39.284, "lon": -87}, {"lat": 39.473, "lon": -93}, {"lat": 41.636, "lon": -87}, {"lat": 41.634, "lon": -87}, {"lat": 41.607, "lon": -87}, {"lat": 43.97, "lon": -89}, {"lat": 46.245, "lon": -119}, {"lat": 46.32, "lon": -121}, {"lat": 48.783, "lon": -119}, {"lat": 22.015, "lon": -105}, {"lat": 22.18, "lon": -104}, {"lat": 22.178, "lon": -104}, {"lat": 22.187, "lon": -104}, {"lat": 22.707, "lon": -103}, {"lat": 22.87, "lon": -103}, {"lat": 22.869, "lon": -103}, {"lat": 22.88, "lon": -103}, {"lat": 22.879, "lon": -103}, {"lat": 23.141, "lon": -103}, {"lat": 22.933, "lon": -105}, {"lat": 22.932, "lon": -105}, {"lat": 23.731, "lon": -99}, {"lat": 23.728, "lon": -99}, {"lat": 28.817, "lon": -107}, {"lat": 31.676, "lon": -113}, {"lat": 31.674, "lon": -113}, {"lat": 33.414, "lon": -111}, {"lat": 33.412, "lon": -111}, {"lat": 34.693, "lon": -106}, {"lat": 34.691, "lon": -106}, {"lat": 34.702, "lon": -106}, {"lat": 34.701, "lon": -106}, {"lat": 33.192, "lon": -115}, {"lat": 36.463, "lon": -100}, {"lat": 36.687, "lon": -102}, {"lat": 36.685, "lon": -102}, {"lat": 36.687, "lon": -102}, {"lat": 36.439, "lon": -120}, {"lat": 36.431, "lon": -120}, {"lat": 36.436, "lon": -120}, {"lat": 36.427, "lon": -120}, {"lat": 30.092, "lon": -91}, {"lat": 36.433, "lon": -120}, {"lat": 36.431, "lon": -120}, {"lat": 36.443, "lon": -120}, {"lat": 36.441, "lon": -120}, {"lat": 36.443, "lon": -120}, {"lat": 36.441, "lon": -120}, {"lat": 36.434, "lon": -120}, {"lat": 36.432, "lon": -120}, {"lat": 34.815, "lon": -79}, {"lat": 34.614, "lon": -78}, {"lat": 34.772, "lon": -79}, {"lat": 34.539, "lon": -79}, {"lat": 34.5, "lon": -79}, {"lat": 34.498, "lon": -79}, {"lat": 34.518, "lon": -79}, {"lat": 34.313, "lon": -79}, {"lat": 33.214, "lon": -80}, {"lat": 32.781, "lon": -81}, {"lat": 32.576, "lon": -82}, {"lat": 32.574, "lon": -82}, {"lat": 32.124, "lon": -83}, {"lat": 32.123, "lon": -83}, {"lat": 31.895, "lon": -82}, {"lat": 31.894, "lon": -82}, {"lat": 31.885, "lon": -82}, {"lat": 31.0, "lon": -83}, {"lat": 30.149, "lon": -82}, {"lat": 29.552, "lon": -83}, {"lat": 29.295, "lon": -81}, {"lat": 29.286, "lon": -81}, {"lat": 28.902, "lon": -82}, {"lat": 28.9, "lon": -82}, {"lat": 28.893, "lon": -82}, {"lat": 28.891, "lon": -82}, {"lat": 28.748, "lon": -82}, {"lat": 28.746, "lon": -82}, {"lat": 27.234, "lon": -82}, {"lat": 27.233, "lon": -82}, {"lat": 26.688, "lon": -81}, {"lat": 26.635, "lon": -81}, {"lat": 26.633, "lon": -81}, {"lat": 26.576, "lon": -81}, {"lat": 26.542, "lon": -81}, {"lat": 26.533, "lon": -81}, {"lat": 26.469, "lon": -81}, {"lat": 22.933, "lon": -82}, {"lat": 22.822, "lon": -82}, {"lat": 22.814, "lon": -82}, {"lat": 22.812, "lon": -82}, {"lat": 22.658, "lon": -81}, {"lat": 22.655, "lon": -81}, {"lat": 22.809, "lon": -83}, {"lat": 22.356, "lon": -80}, {"lat": 39.209, "lon": -109}, {"lat": 37.974, "lon": -104}, {"lat": 37.972, "lon": -104}, {"lat": 22.778, "lon": -82}, {"lat": 22.823, "lon": -82}, {"lat": 22.815, "lon": -82}, {"lat": 22.831, "lon": -82}, {"lat": 22.972, "lon": -83}, {"lat": 22.702, "lon": -98}, {"lat": 22.799, "lon": -99}, {"lat": 22.795, "lon": -99}, {"lat": 22.847, "lon": -99}, {"lat": 22.843, "lon": -99}, {"lat": 33.324, "lon": -82}, {"lat": 33.34, "lon": -82}, {"lat": 33.329, "lon": -82}, {"lat": 46.723, "lon": -119}, {"lat": 45.968, "lon": -119}, {"lat": 45.962, "lon": -119}, {"lat": 39.237, "lon": -122}, {"lat": 39.234, "lon": -122}, {"lat": 37.513, "lon": -121}, {"lat": 37.456, "lon": -121}, {"lat": 37.505, "lon": -121}, {"lat": 37.461, "lon": -121}, {"lat": 36.885, "lon": -120}, {"lat": 36.571, "lon": -120}, {"lat": 36.57, "lon": -120}, {"lat": 36.556, "lon": -120}, {"lat": 36.387, "lon": -120}, {"lat": 36.437, "lon": -120}, {"lat": 36.43, "lon": -120}, {"lat": 36.434, "lon": -120}, {"lat": 36.427, "lon": -120}, {"lat": 36.23, "lon": -120}, {"lat": 36.223, "lon": -120}, {"lat": 22.846, "lon": -99}, {"lat": 25.056, "lon": -100}, {"lat": 25.051, "lon": -100}, {"lat": 27.19, "lon": -90}, {"lat": 29.498, "lon": -91}, {"lat": 29.497, "lon": -91}, {"lat": 29.508, "lon": -91}, {"lat": 29.506, "lon": -91}, {"lat": 29.641, "lon": -91}, {"lat": 31.114, "lon": -89}, {"lat": 31.388, "lon": -88}, {"lat": 38.417, "lon": -94}, {"lat": 39.017, "lon": -96}, {"lat": 39.015, "lon": -96}, {"lat": 42.698, "lon": -98}, {"lat": 32.388, "lon": -115}, {"lat": 32.387, "lon": -115}, {"lat": 32.53, "lon": -115}, {"lat": 32.528, "lon": -115}, {"lat": 33.97, "lon": -118}, {"lat": 35.656, "lon": -119}, {"lat": 35.948, "lon": -119}, {"lat": 35.92, "lon": -119}, {"lat": 35.919, "lon": -119}, {"lat": 36.121, "lon": -119}, {"lat": 36.23, "lon": -120}, {"lat": 36.228, "lon": -120}, {"lat": 36.393, "lon": -120}, {"lat": 36.478, "lon": -120}, {"lat": 36.487, "lon": -120}, {"lat": 36.429, "lon": -120}, {"lat": 36.427, "lon": -120}, {"lat": 36.438, "lon": -120}, {"lat": 36.436, "lon": -120}, {"lat": 36.562, "lon": -120}, {"lat": 36.56, "lon": -120}, {"lat": 36.668, "lon": -119}, {"lat": 36.636, "lon": -120}, {"lat": 36.711, "lon": -120}, {"lat": 36.686, "lon": -121}, {"lat": 36.893, "lon": -120}, {"lat": 37.459, "lon": -121}, {"lat": 37.457, "lon": -121}, {"lat": 37.504, "lon": -121}, {"lat": 38.27, "lon": -121}, {"lat": 38.26, "lon": -121}, {"lat": 38.784, "lon": -123}, {"lat": 38.782, "lon": -123}, {"lat": 39.282, "lon": -122}, {"lat": 42.048, "lon": -122}, {"lat": 46.338, "lon": -119}, {"lat": 46.723, "lon": -119}, {"lat": 48.644, "lon": -119}, {"lat": 26.889, "lon": -101}, {"lat": 22.794, "lon": -99}, {"lat": 23.033, "lon": -99}, {"lat": 23.031, "lon": -99}, {"lat": 25.477, "lon": -100}, {"lat": 25.721, "lon": -100}, {"lat": 36.435, "lon": -120}, {"lat": 36.433, "lon": -120}, {"lat": 30.261, "lon": -91}, {"lat": 30.263, "lon": -91}, {"lat": 36.439, "lon": -120}, {"lat": 36.45, "lon": -120}, {"lat": 36.446, "lon": -120}, {"lat": 36.443, "lon": -120}, {"lat": 26.832, "lon": -82}, {"lat": 26.833, "lon": -82}, {"lat": 41.637, "lon": -87}, {"lat": 41.635, "lon": -87}, {"lat": 39.625, "lon": -96}, {"lat": 39.623, "lon": -96}, {"lat": 38.694, "lon": -90}, {"lat": 38.692, "lon": -90}, {"lat": 39.379, "lon": -96}, {"lat": 39.013, "lon": -96}, {"lat": 39.095, "lon": -97}, {"lat": 39.093, "lon": -97}, {"lat": 38.477, "lon": -95}, {"lat": 38.371, "lon": -95}, {"lat": 38.108, "lon": -95}, {"lat": 38.407, "lon": -99}, {"lat": 38.405, "lon": -99}, {"lat": 38.407, "lon": -99}, {"lat": 38.405, "lon": -99}, {"lat": 37.811, "lon": -98}, {"lat": 36.042, "lon": -97}, {"lat": 36.041, "lon": -97}, {"lat": 34.815, "lon": -96}, {"lat": 22.038, "lon": -79}, {"lat": 22.342, "lon": -80}, {"lat": 22.368, "lon": -80}, {"lat": 22.344, "lon": -81}, {"lat": 22.399, "lon": -81}, {"lat": 22.747, "lon": -81}, {"lat": 22.729, "lon": -81}, {"lat": 22.782, "lon": -81}, {"lat": 22.784, "lon": -81}, {"lat": 22.782, "lon": -81}, {"lat": 22.95, "lon": -81}, {"lat": 22.725, "lon": -83}, {"lat": 22.986, "lon": -83}, {"lat": 46.728, "lon": -119}, {"lat": 46.542, "lon": -120}, {"lat": 46.234, "lon": -120}, {"lat": 45.998, "lon": -119}, {"lat": 45.994, "lon": -119}, {"lat": 39.709, "lon": -122}, {"lat": 39.704, "lon": -122}, {"lat": 39.525, "lon": -122}, {"lat": 39.519, "lon": -122}, {"lat": 39.214, "lon": -122}, {"lat": 39.217, "lon": -122}, {"lat": 39.012, "lon": -122}, {"lat": 38.945, "lon": -122}, {"lat": 38.943, "lon": -122}, {"lat": 38.9, "lon": -122}, {"lat": 37.665, "lon": -114}, {"lat": 38.371, "lon": -122}, {"lat": 38.36, "lon": -122}, {"lat": 38.176, "lon": -121}, {"lat": 38.176, "lon": -121}, {"lat": 37.043, "lon": -114}, {"lat": 37.965, "lon": -121}, {"lat": 37.963, "lon": -121}, {"lat": 37.962, "lon": -121}, {"lat": 37.647, "lon": -121}, {"lat": 37.582, "lon": -121}, {"lat": 36.981, "lon": -118}, {"lat": 36.932, "lon": -120}, {"lat": 36.91, "lon": -120}, {"lat": 36.923, "lon": -120}, {"lat": 36.727, "lon": -119}, {"lat": 36.725, "lon": -119}, {"lat": 36.772, "lon": -120}, {"lat": 36.714, "lon": -120}, {"lat": 36.682, "lon": -120}, {"lat": 36.681, "lon": -120}, {"lat": 36.565, "lon": -120}, {"lat": 36.588, "lon": -120}, {"lat": 36.552, "lon": -120}, {"lat": 36.531, "lon": -120}, {"lat": 36.529, "lon": -120}, {"lat": 36.563, "lon": -120}, {"lat": 36.562, "lon": -120}, {"lat": 36.563, "lon": -120}, {"lat": 36.553, "lon": -120}, {"lat": 36.446, "lon": -120}, {"lat": 36.445, "lon": -120}, {"lat": 36.436, "lon": -120}, {"lat": 36.434, "lon": -120}, {"lat": 36.438, "lon": -120}, {"lat": 36.436, "lon": -120}, {"lat": 36.344, "lon": -120}, {"lat": 36.153, "lon": -120}, {"lat": 36.151, "lon": -120}, {"lat": 35.896, "lon": -119}, {"lat": 35.895, "lon": -119}, {"lat": 35.548, "lon": -119}, {"lat": 35.547, "lon": -119}, {"lat": 34.473, "lon": -112}, {"lat": 35.638, "lon": -120}, {"lat": 34.465, "lon": -112}, {"lat": 34.463, "lon": -112}, {"lat": 35.224, "lon": -119}, {"lat": 32.633, "lon": -115}, {"lat": 32.631, "lon": -115}, {"lat": 32.624, "lon": -115}, {"lat": 32.622, "lon": -115}]}