{"DataSet": "MODIS", "Date": "2021-03-03_1838", "coordinates": [{"lat": 22.184, "lon": -80.959}, {"lat": 22.744, "lon": -80.065}, {"lat": 22.743, "lon": -80.075}, {"lat": 22.749, "lon": -80.072}, {"lat": 28.524, "lon": -88.304}, {"lat": 22.19, "lon": -99.201}, {"lat": 25.069, "lon": -100.27}, {"lat": 25.071, "lon": -100.276}, {"lat": 33.411, "lon": -110.865}, {"lat": 33.422, "lon": -110.868}, {"lat": 33.414, "lon": -110.854}, {"lat": 33.411, "lon": -110.87}, {"lat": 33.425, "lon": -110.857}, {"lat": 33.422, "lon": -110.873}, {"lat": 27.612, "lon": -82.262}, {"lat": 26.952, "lon": -80.292}, {"lat": 26.799, "lon": -81.087}, {"lat": 26.727, "lon": -81.129}, {"lat": 23.041, "lon": -98.808}, {"lat": 23.04, "lon": -98.798}, {"lat": 22.057, "lon": -98.369}, {"lat": 40.622, "lon": -95.039}, {"lat": 40.359, "lon": -102.029}, {"lat": 40.357, "lon": -102.002}, {"lat": 38.697, "lon": -90.142}, {"lat": 38.694, "lon": -90.129}, {"lat": 39.005, "lon": -95.048}, {"lat": 38.995, "lon": -95.111}, {"lat": 38.357, "lon": -91.724}, {"lat": 38.215, "lon": -91.717}, {"lat": 37.888, "lon": -95.162}, {"lat": 37.886, "lon": -95.15}, {"lat": 37.561, "lon": -93.969}, {"lat": 37.281, "lon": -95.44}, {"lat": 37.28, "lon": -95.428}, {"lat": 36.882, "lon": -94.82}, {"lat": 30.796, "lon": -88.583}, {"lat": 30.797, "lon": -88.588}, {"lat": 48.792, "lon": -119.391}, {"lat": 48.792, "lon": -119.399}, {"lat": 46.726, "lon": -119.211}, {"lat": 46.327, "lon": -120.647}, {"lat": 46.325, "lon": -120.63}, {"lat": 40.543, "lon": -122.056}, {"lat": 40.29, "lon": -122.338}, {"lat": 40.288, "lon": -122.323}, {"lat": 38.919, "lon": -122.614}, {"lat": 38.093, "lon": -121.106}, {"lat": 37.605, "lon": -120.518}, {"lat": 37.384, "lon": -119.251}, {"lat": 37.241, "lon": -120.272}, {"lat": 36.57, "lon": -119.95}, {"lat": 36.568, "lon": -119.939}, {"lat": 36.441, "lon": -120.964}, {"lat": 34.095, "lon": -117.388}, {"lat": 34.119, "lon": -117.82}, {"lat": 22.017, "lon": -78.231}, {"lat": 22.03, "lon": -78.585}, {"lat": 22.033, "lon": -78.591}, {"lat": 22.032, "lon": -78.602}, {"lat": 22.03, "lon": -78.613}, {"lat": 22.043, "lon": -78.592}, {"lat": 22.041, "lon": -78.603}, {"lat": 22.04, "lon": -78.614}, {"lat": 22.051, "lon": -78.605}, {"lat": 22.071, "lon": -80.519}, {"lat": 22.179, "lon": -80.464}, {"lat": 22.242, "lon": -80.933}, {"lat": 22.479, "lon": -80.492}, {"lat": 22.478, "lon": -80.502}, {"lat": 22.406, "lon": -81.708}, {"lat": 22.404, "lon": -81.718}, {"lat": 22.591, "lon": -81.135}, {"lat": 22.589, "lon": -81.144}, {"lat": 22.801, "lon": -81.848}, {"lat": 22.855, "lon": -81.788}, {"lat": 22.854, "lon": -81.797}, {"lat": 22.828, "lon": -81.973}, {"lat": 22.653, "lon": -83.251}, {"lat": 22.659, "lon": -83.247}, {"lat": 22.798, "lon": -82.844}, {"lat": 22.807, "lon": -82.845}, {"lat": 22.93, "lon": -82.582}, {"lat": 22.929, "lon": -82.592}, {"lat": 22.997, "lon": -82.808}, {"lat": 26.005, "lon": -80.934}, {"lat": 26.004, "lon": -80.944}, {"lat": 26.535, "lon": -80.747}, {"lat": 26.534, "lon": -80.757}, {"lat": 26.969, "lon": -80.239}, {"lat": 26.968, "lon": -80.25}, {"lat": 27.167, "lon": -80.416}, {"lat": 27.166, "lon": -80.427}, {"lat": 27.229, "lon": -80.509}, {"lat": 27.227, "lon": -80.52}, {"lat": 27.223, "lon": -82.296}, {"lat": 27.235, "lon": -82.274}, {"lat": 27.234, "lon": -82.284}, {"lat": 27.232, "lon": -82.294}, {"lat": 27.244, "lon": -82.275}, {"lat": 27.442, "lon": -81.383}, {"lat": 27.441, "lon": -81.393}, {"lat": 27.429, "lon": -81.751}, {"lat": 28.489, "lon": -80.55}, {"lat": 28.488, "lon": -80.561}, {"lat": 28.486, "lon": -80.572}, {"lat": 28.497, "lon": -80.563}, {"lat": 29.278, "lon": -81.337}, {"lat": 29.619, "lon": -83.126}, {"lat": 29.883, "lon": -81.893}, {"lat": 29.882, "lon": -81.904}, {"lat": 29.951, "lon": -82.598}, {"lat": 30.037, "lon": -82.779}, {"lat": 30.046, "lon": -84.867}, {"lat": 30.044, "lon": -84.878}, {"lat": 30.058, "lon": -84.915}, {"lat": 30.076, "lon": -84.846}, {"lat": 30.074, "lon": -84.857}, {"lat": 30.478, "lon": -82.324}, {"lat": 30.484, "lon": -82.347}, {"lat": 30.482, "lon": -82.357}, {"lat": 30.478, "lon": -82.389}, {"lat": 30.487, "lon": -82.39}, {"lat": 30.499, "lon": -82.371}, {"lat": 30.497, "lon": -82.381}, {"lat": 30.496, "lon": -82.392}, {"lat": 30.494, "lon": -82.402}, {"lat": 30.323, "lon": -83.598}, {"lat": 30.506, "lon": -82.383}, {"lat": 30.505, "lon": -82.394}, {"lat": 30.332, "lon": -83.6}, {"lat": 30.189, "lon": -84.955}, {"lat": 30.187, "lon": -84.966}, {"lat": 30.198, "lon": -84.957}, {"lat": 30.248, "lon": -85.228}, {"lat": 30.526, "lon": -84.032}, {"lat": 30.652, "lon": -83.497}, {"lat": 30.557, "lon": -84.843}, {"lat": 30.939, "lon": -82.441}, {"lat": 30.938, "lon": -82.451}, {"lat": 30.948, "lon": -82.442}, {"lat": 30.947, "lon": -82.453}, {"lat": 30.77, "lon": -84.252}, {"lat": 30.927, "lon": -83.383}, {"lat": 30.906, "lon": -84.512}, {"lat": 31.304, "lon": -83.884}, {"lat": 31.557, "lon": -82.158}, {"lat": 31.459, "lon": -84.025}, {"lat": 31.659, "lon": -83.417}, {"lat": 31.659, "lon": -83.67}, {"lat": 31.668, "lon": -83.671}, {"lat": 31.63, "lon": -84.051}, {"lat": 31.673, "lon": -83.823}, {"lat": 31.831, "lon": -83.185}, {"lat": 32.171, "lon": -81.048}, {"lat": 32.175, "lon": -81.055}, {"lat": 31.94, "lon": -82.856}, {"lat": 31.939, "lon": -82.867}, {"lat": 32.185, "lon": -82.073}, {"lat": 31.929, "lon": -84.214}, {"lat": 32.052, "lon": -84.137}, {"lat": 32.64, "lon": -80.802}, {"lat": 32.475, "lon": -82.168}, {"lat": 32.496, "lon": -82.081}, {"lat": 32.628, "lon": -81.177}, {"lat": 32.626, "lon": -81.189}, {"lat": 32.354, "lon": -83.52}, {"lat": 32.363, "lon": -83.521}, {"lat": 32.333, "lon": -83.731}, {"lat": 32.331, "lon": -83.742}, {"lat": 32.448, "lon": -83.116}, {"lat": 32.374, "lon": -83.632}, {"lat": 32.373, "lon": -83.642}, {"lat": 32.724, "lon": -81.053}, {"lat": 32.549, "lon": -82.439}, {"lat": 32.547, "lon": -82.45}, {"lat": 31.854, "lon": -86.956}, {"lat": 32.315, "lon": -84.166}, {"lat": 32.814, "lon": -80.957}, {"lat": 32.812, "lon": -80.969}, {"lat": 32.664, "lon": -82.612}, {"lat": 32.663, "lon": -82.623}, {"lat": 33.002, "lon": -79.983}, {"lat": 32.752, "lon": -82.844}, {"lat": 32.746, "lon": -82.887}, {"lat": 32.913, "lon": -81.699}, {"lat": 33.18, "lon": -79.551}, {"lat": 32.633, "lon": -83.948}, {"lat": 33.026, "lon": -81.235}, {"lat": 33.055, "lon": -81.08}, {"lat": 32.651, "lon": -84.267}, {"lat": 32.967, "lon": -82.046}, {"lat": 32.082, "lon": -87.935}, {"lat": 33.174, "lon": -81.516}, {"lat": 33.173, "lon": -81.527}, {"lat": 33.119, "lon": -81.953}, {"lat": 33.184, "lon": -81.517}, {"lat": 33.182, "lon": -81.529}, {"lat": 33.02, "lon": -82.772}, {"lat": 33.156, "lon": -82.299}, {"lat": 33.013, "lon": -83.347}, {"lat": 32.974, "lon": -83.753}, {"lat": 32.973, "lon": -83.764}, {"lat": 33.541, "lon": -79.691}, {"lat": 33.552, "lon": -79.868}, {"lat": 33.095, "lon": -83.556}, {"lat": 33.104, "lon": -83.558}, {"lat": 33.232, "lon": -83.096}, {"lat": 33.231, "lon": -83.107}, {"lat": 33.161, "lon": -83.608}, {"lat": 33.358, "lon": -82.44}, {"lat": 33.367, "lon": -82.442}, {"lat": 33.752, "lon": -79.311}, {"lat": 33.717, "lon": -81.062}, {"lat": 33.434, "lon": -83.375}, {"lat": 33.682, "lon": -81.93}, {"lat": 33.858, "lon": -82.21}, {"lat": 39.48, "lon": -84.387}, {"lat": 39.286, "lon": -87.244}, {"lat": 39.284, "lon": -87.256}, {"lat": 39.473, "lon": -93.368}, {"lat": 41.636, "lon": -87.139}, {"lat": 41.634, "lon": -87.15}, {"lat": 41.607, "lon": -87.33}, {"lat": 43.97, "lon": -89.343}, {"lat": 46.245, "lon": -118.845}, {"lat": 46.32, "lon": -120.641}, {"lat": 48.783, "lon": -119.419}, {"lat": 22.015, "lon": -105.117}, {"lat": 22.18, "lon": -104.455}, {"lat": 22.178, "lon": -104.465}, {"lat": 22.187, "lon": -104.462}, {"lat": 22.707, "lon": -102.703}, {"lat": 22.87, "lon": -102.944}, {"lat": 22.869, "lon": -102.955}, {"lat": 22.88, "lon": -102.945}, {"lat": 22.879, "lon": -102.957}, {"lat": 23.141, "lon": -103.131}, {"lat": 22.933, "lon": -104.853}, {"lat": 22.932, "lon": -104.863}, {"lat": 23.731, "lon": -99.07}, {"lat": 23.728, "lon": -99.074}, {"lat": 28.817, "lon": -107.013}, {"lat": 31.676, "lon": -112.61}, {"lat": 31.674, "lon": -112.624}, {"lat": 33.414, "lon": -110.854}, {"lat": 33.412, "lon": -110.865}, {"lat": 34.693, "lon": -105.704}, {"lat": 34.691, "lon": -105.717}, {"lat": 34.702, "lon": -105.706}, {"lat": 34.701, "lon": -105.719}, {"lat": 33.192, "lon": -115.464}, {"lat": 36.463, "lon": -99.574}, {"lat": 36.687, "lon": -101.995}, {"lat": 36.685, "lon": -102.019}, {"lat": 36.687, "lon": -102.001}, {"lat": 36.439, "lon": -120.365}, {"lat": 36.431, "lon": -120.399}, {"lat": 36.436, "lon": -120.371}, {"lat": 36.427, "lon": -120.405}, {"lat": 30.092, "lon": -90.953}, {"lat": 36.433, "lon": -120.376}, {"lat": 36.431, "lon": -120.389}, {"lat": 36.443, "lon": -120.378}, {"lat": 36.441, "lon": -120.392}, {"lat": 36.443, "lon": -120.388}, {"lat": 36.441, "lon": -120.376}, {"lat": 36.434, "lon": -120.39}, {"lat": 36.432, "lon": -120.378}, {"lat": 34.815, "lon": -78.624}, {"lat": 34.614, "lon": -77.924}, {"lat": 34.772, "lon": -78.983}, {"lat": 34.539, "lon": -78.808}, {"lat": 34.5, "lon": -78.694}, {"lat": 34.498, "lon": -78.682}, {"lat": 34.518, "lon": -78.953}, {"lat": 34.313, "lon": -78.832}, {"lat": 33.214, "lon": -79.889}, {"lat": 32.781, "lon": -81.085}, {"lat": 32.576, "lon": -81.688}, {"lat": 32.574, "lon": -81.678}, {"lat": 32.124, "lon": -82.654}, {"lat": 32.123, "lon": -82.643}, {"lat": 31.895, "lon": -81.577}, {"lat": 31.894, "lon": -81.567}, {"lat": 31.885, "lon": -81.575}, {"lat": 31.0, "lon": -83.304}, {"lat": 30.149, "lon": -81.878}, {"lat": 29.552, "lon": -82.641}, {"lat": 29.295, "lon": -81.426}, {"lat": 29.286, "lon": -81.428}, {"lat": 28.902, "lon": -82.237}, {"lat": 28.9, "lon": -82.227}, {"lat": 28.893, "lon": -82.239}, {"lat": 28.891, "lon": -82.229}, {"lat": 28.748, "lon": -82.012}, {"lat": 28.746, "lon": -82.002}, {"lat": 27.234, "lon": -82.259}, {"lat": 27.233, "lon": -82.249}, {"lat": 26.688, "lon": -80.899}, {"lat": 26.635, "lon": -80.749}, {"lat": 26.633, "lon": -80.737}, {"lat": 26.576, "lon": -80.632}, {"lat": 26.542, "lon": -80.75}, {"lat": 26.533, "lon": -80.752}, {"lat": 26.469, "lon": -80.748}, {"lat": 22.933, "lon": -81.816}, {"lat": 22.822, "lon": -81.697}, {"lat": 22.814, "lon": -81.71}, {"lat": 22.812, "lon": -81.699}, {"lat": 22.658, "lon": -80.827}, {"lat": 22.655, "lon": -80.988}, {"lat": 22.809, "lon": -82.661}, {"lat": 22.356, "lon": -80.371}, {"lat": 39.209, "lon": -108.773}, {"lat": 37.974, "lon": -103.657}, {"lat": 37.972, "lon": -103.645}, {"lat": 22.778, "lon": -81.911}, {"lat": 22.823, "lon": -82.345}, {"lat": 22.815, "lon": -82.349}, {"lat": 22.831, "lon": -82.351}, {"lat": 22.972, "lon": -82.509}, {"lat": 22.702, "lon": -98.041}, {"lat": 22.799, "lon": -98.935}, {"lat": 22.795, "lon": -98.956}, {"lat": 22.847, "lon": -99.034}, {"lat": 22.843, "lon": -99.056}, {"lat": 33.324, "lon": -81.558}, {"lat": 33.34, "lon": -81.564}, {"lat": 33.329, "lon": -81.565}, {"lat": 46.723, "lon": -119.223}, {"lat": 45.968, "lon": -118.561}, {"lat": 45.962, "lon": -118.537}, {"lat": 39.237, "lon": -121.64}, {"lat": 39.234, "lon": -121.647}, {"lat": 37.513, "lon": -120.91}, {"lat": 37.456, "lon": -120.845}, {"lat": 37.505, "lon": -120.918}, {"lat": 37.461, "lon": -120.848}, {"lat": 36.885, "lon": -120.099}, {"lat": 36.571, "lon": -119.89}, {"lat": 36.57, "lon": -119.897}, {"lat": 36.556, "lon": -119.903}, {"lat": 36.387, "lon": -119.654}, {"lat": 36.437, "lon": -120.391}, {"lat": 36.43, "lon": -120.361}, {"lat": 36.434, "lon": -120.398}, {"lat": 36.427, "lon": -120.368}, {"lat": 36.23, "lon": -120.249}, {"lat": 36.223, "lon": -120.218}, {"lat": 22.846, "lon": -99.041}, {"lat": 25.056, "lon": -100.277}, {"lat": 25.051, "lon": -100.302}, {"lat": 27.19, "lon": -90.032}, {"lat": 29.498, "lon": -90.82}, {"lat": 29.497, "lon": -90.832}, {"lat": 29.508, "lon": -90.821}, {"lat": 29.506, "lon": -90.833}, {"lat": 29.641, "lon": -91.31}, {"lat": 31.114, "lon": -89.102}, {"lat": 31.388, "lon": -88.331}, {"lat": 38.417, "lon": -94.176}, {"lat": 39.017, "lon": -96.204}, {"lat": 39.015, "lon": -96.215}, {"lat": 42.698, "lon": -97.636}, {"lat": 32.388, "lon": -115.219}, {"lat": 32.387, "lon": -115.212}, {"lat": 32.53, "lon": -115.394}, {"lat": 32.528, "lon": -115.408}, {"lat": 33.97, "lon": -117.634}, {"lat": 35.656, "lon": -119.325}, {"lat": 35.948, "lon": -119.01}, {"lat": 35.92, "lon": -119.286}, {"lat": 35.919, "lon": -119.297}, {"lat": 36.121, "lon": -119.023}, {"lat": 36.23, "lon": -120.228}, {"lat": 36.228, "lon": -120.239}, {"lat": 36.393, "lon": -119.656}, {"lat": 36.478, "lon": -119.578}, {"lat": 36.487, "lon": -119.58}, {"lat": 36.429, "lon": -120.381}, {"lat": 36.427, "lon": -120.392}, {"lat": 36.438, "lon": -120.383}, {"lat": 36.436, "lon": -120.394}, {"lat": 36.562, "lon": -119.899}, {"lat": 36.56, "lon": -119.91}, {"lat": 36.668, "lon": -119.4}, {"lat": 36.636, "lon": -119.704}, {"lat": 36.711, "lon": -119.955}, {"lat": 36.686, "lon": -120.583}, {"lat": 36.893, "lon": -120.099}, {"lat": 37.459, "lon": -120.851}, {"lat": 37.457, "lon": -120.862}, {"lat": 37.504, "lon": -120.919}, {"lat": 38.27, "lon": -120.532}, {"lat": 38.26, "lon": -120.669}, {"lat": 38.784, "lon": -123.053}, {"lat": 38.782, "lon": -123.065}, {"lat": 39.282, "lon": -121.583}, {"lat": 42.048, "lon": -121.617}, {"lat": 46.338, "lon": -118.746}, {"lat": 46.723, "lon": -119.218}, {"lat": 48.644, "lon": -119.46}, {"lat": 26.889, "lon": -101.46}, {"lat": 22.794, "lon": -98.928}, {"lat": 23.033, "lon": -99.065}, {"lat": 23.031, "lon": -99.075}, {"lat": 25.477, "lon": -100.011}, {"lat": 25.721, "lon": -100.304}, {"lat": 36.435, "lon": -120.374}, {"lat": 36.433, "lon": -120.397}, {"lat": 30.261, "lon": -91.178}, {"lat": 30.263, "lon": -91.184}, {"lat": 36.439, "lon": -120.385}, {"lat": 36.45, "lon": -120.389}, {"lat": 36.446, "lon": -120.384}, {"lat": 36.443, "lon": -120.389}, {"lat": 26.832, "lon": -81.892}, {"lat": 26.833, "lon": -81.896}, {"lat": 41.637, "lon": -87.147}, {"lat": 41.635, "lon": -87.134}, {"lat": 39.625, "lon": -96.013}, {"lat": 39.623, "lon": -95.996}, {"lat": 38.694, "lon": -90.142}, {"lat": 38.692, "lon": -90.13}, {"lat": 39.379, "lon": -95.947}, {"lat": 39.013, "lon": -96.154}, {"lat": 39.095, "lon": -97.153}, {"lat": 39.093, "lon": -97.133}, {"lat": 38.477, "lon": -94.53}, {"lat": 38.371, "lon": -95.035}, {"lat": 38.108, "lon": -94.86}, {"lat": 38.407, "lon": -98.686}, {"lat": 38.405, "lon": -98.662}, {"lat": 38.407, "lon": -98.692}, {"lat": 38.405, "lon": -98.668}, {"lat": 37.811, "lon": -98.167}, {"lat": 36.042, "lon": -97.392}, {"lat": 36.041, "lon": -97.374}, {"lat": 34.815, "lon": -95.909}, {"lat": 22.038, "lon": -78.619}, {"lat": 22.342, "lon": -80.008}, {"lat": 22.368, "lon": -79.97}, {"lat": 22.344, "lon": -81.005}, {"lat": 22.399, "lon": -80.867}, {"lat": 22.747, "lon": -80.857}, {"lat": 22.729, "lon": -81.232}, {"lat": 22.782, "lon": -81.218}, {"lat": 22.784, "lon": -81.211}, {"lat": 22.782, "lon": -81.223}, {"lat": 22.95, "lon": -80.676}, {"lat": 22.725, "lon": -82.818}, {"lat": 22.986, "lon": -83.046}, {"lat": 46.728, "lon": -119.224}, {"lat": 46.542, "lon": -119.552}, {"lat": 46.234, "lon": -119.949}, {"lat": 45.998, "lon": -118.562}, {"lat": 45.994, "lon": -118.569}, {"lat": 39.709, "lon": -122.064}, {"lat": 39.704, "lon": -122.072}, {"lat": 39.525, "lon": -122.32}, {"lat": 39.519, "lon": -122.306}, {"lat": 39.214, "lon": -121.709}, {"lat": 39.217, "lon": -121.714}, {"lat": 39.012, "lon": -122.105}, {"lat": 38.945, "lon": -122.099}, {"lat": 38.943, "lon": -122.079}, {"lat": 38.9, "lon": -121.739}, {"lat": 37.665, "lon": -113.578}, {"lat": 38.371, "lon": -122.032}, {"lat": 38.36, "lon": -122.176}, {"lat": 38.176, "lon": -121.282}, {"lat": 38.176, "lon": -121.289}, {"lat": 37.043, "lon": -113.628}, {"lat": 37.965, "lon": -121.094}, {"lat": 37.963, "lon": -121.101}, {"lat": 37.962, "lon": -121.084}, {"lat": 37.647, "lon": -120.793}, {"lat": 37.582, "lon": -121.047}, {"lat": 36.981, "lon": -118.225}, {"lat": 36.932, "lon": -119.835}, {"lat": 36.91, "lon": -119.724}, {"lat": 36.923, "lon": -120.107}, {"lat": 36.727, "lon": -119.46}, {"lat": 36.725, "lon": -119.447}, {"lat": 36.772, "lon": -120.295}, {"lat": 36.714, "lon": -120.154}, {"lat": 36.682, "lon": -119.868}, {"lat": 36.681, "lon": -119.854}, {"lat": 36.565, "lon": -119.557}, {"lat": 36.588, "lon": -119.933}, {"lat": 36.552, "lon": -119.614}, {"lat": 36.531, "lon": -119.521}, {"lat": 36.529, "lon": -119.508}, {"lat": 36.563, "lon": -119.894}, {"lat": 36.562, "lon": -119.88}, {"lat": 36.563, "lon": -119.887}, {"lat": 36.553, "lon": -119.889}, {"lat": 36.446, "lon": -120.396}, {"lat": 36.445, "lon": -120.381}, {"lat": 36.436, "lon": -120.398}, {"lat": 36.434, "lon": -120.383}, {"lat": 36.438, "lon": -120.389}, {"lat": 36.436, "lon": -120.374}, {"lat": 36.344, "lon": -119.837}, {"lat": 36.153, "lon": -120.125}, {"lat": 36.151, "lon": -120.11}, {"lat": 35.896, "lon": -119.082}, {"lat": 35.895, "lon": -119.069}, {"lat": 35.548, "lon": -119.157}, {"lat": 35.547, "lon": -119.144}, {"lat": 34.473, "lon": -112.451}, {"lat": 35.638, "lon": -120.421}, {"lat": 34.465, "lon": -112.467}, {"lat": 34.463, "lon": -112.453}, {"lat": 35.224, "lon": -118.92}, {"lat": 32.633, "lon": -114.62}, {"lat": 32.631, "lon": -114.608}, {"lat": 32.624, "lon": -114.622}, {"lat": 32.622, "lon": -114.611}]}